{
  "viam-cartographer": {
    "mock_data": {
      "lidar": {
        "0.pcd": {
          "hash": "32b95e765b10c1cfc6097eebc74bbe64",
          "size": 9880
        },
        "1.pcd": {
          "hash": "a038d9f7ad0356704d512402ead3665b",
          "size": 9928
        },
        "10.pcd": {
          "hash": "7ffd7681874dd36a8c435a4718e472bc",
          "size": 10000
        },
        "11.pcd": {
          "hash": "ef95af97b5ed0bc9587cb19dd487f03e",
          "size": 9880
        },
        "12.pcd": {
          "hash": "592da217520e0a6874ce8387451b59aa",
          "size": 9868
        },
        "13.pcd": {
          "hash": "1a696bfed9c0cc93d16f76f8c3e295f8",
          "size": 10000
        },
        "14.pcd": {
          "hash": "3049df7aa2bcde37d068979abc869a3a",
          "size": 9952
        },
        "15.pcd": {
          "hash": "f001078e01a4104fdfca8294eef99210",
          "size": 9952
        },
        "16.pcd": {
          "hash": "e1b7aa85857575d275a40b61ed896400",
          "size": 9964
        },
        "2.pcd": {
          "hash": "924d493bc3ba60a72cb3acad7205663e",
          "size": 9952
        },
        "3.pcd": {
          "hash": "be52a00e9edab3873e76bc38283e956d",
          "size": 10036
        },
        "4.pcd": {
          "hash": "d38b3e6275ada37dfd3a5b1ad8518b41",
          "size": 10012
        },
        "5.pcd": {
          "hash": "41ecd45e566babf33d0e46b57f7f5d91",
          "size": 9964
        },
        "6.pcd": {
          "hash": "5076d6681530bd995e9155f70dc5fd41",
          "size": 9928
        },
        "7.pcd": {
          "hash": "6738b43810d9bdb2f93c392d6a71b96b",
          "size": 10000
        },
        "8.pcd": {
          "hash": "fc8e932ef4ceac3abcb3dc85fc5f970e",
          "size": 10060
        },
        "9.pcd": {
          "hash": "10e2501cedc4900d542e81e6f4391189",
          "size": 9916
        }
      },
      "movement_sensor": {
        "data.txt": {
          "hash": "2b41e7cb9d3f9db51a3fd94f23766e50",
          "size": 4242
        }
      }
    },
    "mock_lidar": {
      "0.pcd": {
        "hash": "fc063341f9586fcddc69df23f2870de7",
        "size": 14515
      },
      "1.pcd": {
        "hash": "6224fee6b391f47065bfa47888d45653",
        "size": 14608
      },
      "10.pcd": {
        "hash": "7e88a8c8f2984a2f80e7520750ef8ed6",
        "size": 11819
      },
      "11.pcd": {
        "hash": "920a7d31cc9e0d0ed653e324cd7b9c0b",
        "size": 11504
      },
      "12.pcd": {
        "hash": "b93d4aeca9afeeaa8d957a064046d038",
        "size": 13046
      },
      "13.pcd": {
        "hash": "20c64154436219e02cf46c78d5bc957b",
        "size": 12886
      },
      "14.pcd": {
        "hash": "52e7b47d219eeebd376144d194cb1ef6",
        "size": 13145
      },
      "2.pcd": {
        "hash": "dd2b53df2ecbdb82a947a46181c97d81",
        "size": 14533
      },
      "3.pcd": {
        "hash": "ceac62444e263fa56bb28ebe385f5e39",
        "size": 14321
      },
      "4.pcd": {
        "hash": "fa68ea21466139291050757db6f659f8",
        "size": 12505
      },
      "5.pcd": {
        "hash": "b23a38abda5a5a2ca8f3d984ec5ad485",
        "size": 12907
      },
      "6.pcd": {
        "hash": "1038efa3cfc505c8267b396294b4e7ba",
        "size": 12843
      },
      "7.pcd": {
        "hash": "026577760a5dc6140340a427b521de46",
        "size": 13084
      },
      "8.pcd": {
        "hash": "94c7f4aac73e4f95fb1e450d782952b3",
        "size": 13164
      },
      "9.pcd": {
        "hash": "21142d5fae5a707da9f7c36dac3ead54",
        "size": 10709
      }
    },
    "outputs": {
      "viam-office-02-22-3": {
        "internal_state": {
          "internal_state_0.pbstream": {
            "hash": "4e317c3318efbfcf6263576d69ab0cfe",
            "size": 25587
          },
          "internal_state_1.pbstream": {
            "hash": "48d89499c61bd8f76650a507e7a3b4cd",
            "size": 1734264
          },
          "internal_state_10.pbstream": {
            "hash": "5ca494732cc1db2dde22b3ba50c69865",
            "size": 14785355
          },
          "internal_state_11.pbstream": {
            "hash": "5cfb82e78705ceb50af8a975a7bedd64",
            "size": 16414381
          },
          "internal_state_12.pbstream": {
            "hash": "c24824d0283752ea564af16c27a18956",
            "size": 17204237
          },
          "internal_state_13.pbstream": {
            "hash": "34eb19953aa84712dc5fc6d21310a908",
            "size": 18530440
          },
          "internal_state_14.pbstream": {
            "hash": "17f8c0a90487dd34f5da97f09a90b4e0",
            "size": 20517391
          },
          "internal_state_15.pbstream": {
            "hash": "233e32227442be90c597033d9c3629e3",
            "size": 22105695
          },
          "internal_state_16.pbstream": {
            "hash": "ca3fdb9e13e5aab1da88cd1265fabb40",
            "size": 23564379
          },
          "internal_state_17.pbstream": {
            "hash": "cf82ec0cd5c0f422efe870bd71b2dfa2",
            "size": 23421652
          },
          "internal_state_18.pbstream": {
            "hash": "c6eead2b36faf0fdd635b31e4e30a3cf",
            "size": 25595699
          },
          "internal_state_19.pbstream": {
            "hash": "0c2a41fa31c52e4bd329d8e9c87322ed",
            "size": 27326595
          },
          "internal_state_2.pbstream": {
            "hash": "044299335f4601eee0526258699f3ae8",
            "size": 3092991
          },
          "internal_state_20.pbstream": {
            "hash": "22176dbb25fcb1c604bd16d429bf50f8",
            "size": 28605187
          },
          "internal_state_21.pbstream": {
            "hash": "81e6029650f2c4786c34ed370a315b47",
            "size": 29496163
          },
          "internal_state_22.pbstream": {
            "hash": "3924406b422d445d2857d1ef44ebbfbf",
            "size": 30823897
          },
          "internal_state_23.pbstream": {
            "hash": "8400b254ecb5e01b1d1fed910dd9be68",
            "size": 31886472
          },
          "internal_state_3.pbstream": {
            "hash": "7991319dbd9440005fbd59b8718c7770",
            "size": 4471123
          },
          "internal_state_4.pbstream": {
            "hash": "db2a444867ef121074e273af5070c217",
            "size": 5898278
          },
          "internal_state_5.pbstream": {
            "hash": "78d0e83609c6fcb29497a9515e9c9302",
            "size": 7334930
          },
          "internal_state_6.pbstream": {
            "hash": "99091c95873b82a90db4c16d94e572ba",
            "size": 7424545
          },
          "internal_state_7.pbstream": {
            "hash": "cea159126ab87b732484bf09e21d33ee",
            "size": 10963795
          },
          "internal_state_8.pbstream": {
            "hash": "6f07ec93b9a7782babd0a9fc22fbd96f",
            "size": 12676027
          },
          "internal_state_9.pbstream": {
            "hash": "c010d29f87022e88028ea10370a17eda",
            "size": 13865933
          }
        },
        "pointcloud": {
          "pointcloud_0.pcd": {
            "hash": "2f41517f96ddcbbd838c781204707590",
            "size": 302266
          },
          "pointcloud_1.pcd": {
            "hash": "f9a36fd5c329d053678a961ec6f51b40",
            "size": 2641372
          },
          "pointcloud_10.pcd": {
            "hash": "090e0d5c2d8a0214b354ca11df07f9fb",
            "size": 14087260
          },
          "pointcloud_11.pcd": {
            "hash": "80c73e98e6eaab752da6221da8eece67",
            "size": 16277038
          },
          "pointcloud_12.pcd": {
            "hash": "7300780bd50d95a42304c3444f20b030",
            "size": 16236686
          },
          "pointcloud_13.pcd": {
            "hash": "76700950faf27a9297822f3a1a5d5cb4",
            "size": 16165550
          },
          "pointcloud_14.pcd": {
            "hash": "8e0e900389db448d77c91a99b8bf478c",
            "size": 17590558
          },
          "pointcloud_15.pcd": {
            "hash": "ca8054ef766aa4bd69ddd74d27a8fbaf",
            "size": 17697534
          },
          "pointcloud_16.pcd": {
            "hash": "1ee6491f6b18cfb9194a20f352c7b647",
            "size": 18331774
          },
          "pointcloud_17.pcd": {
            "hash": "9e1989dfaf47c44aee0fb779085c34a8",
            "size": 19232718
          },
          "pointcloud_18.pcd": {
            "hash": "791b4e8d29df799c9af075079bcfc466",
            "size": 18491998
          },
          "pointcloud_19.pcd": {
            "hash": "af6e9b6cc2dc501fbdc763e271d26a49",
            "size": 17712062
          },
          "pointcloud_2.pcd": {
            "hash": "0d5c88ec209d520e9ddfe2003d30c969",
            "size": 4822460
          },
          "pointcloud_20.pcd": {
            "hash": "253fbfa8768b90d67224599dbf980d35",
            "size": 17642990
          },
          "pointcloud_21.pcd": {
            "hash": "9425807069558e90b104cc86ddc93bce",
            "size": 17588862
          },
          "pointcloud_22.pcd": {
            "hash": "807d0a0d1e4350533db1d2902fab7281",
            "size": 17240494
          },
          "pointcloud_23.pcd": {
            "hash": "bcf8dbab0f3811f06a4231e2c10076c3",
            "size": 17306606
          },
          "pointcloud_3.pcd": {
            "hash": "dc62b2a27bf4ee6f2323e801dbcaaf28",
            "size": 5844492
          },
          "pointcloud_4.pcd": {
            "hash": "dd7b9ec745aa1d1f7c4c068a816889b1",
            "size": 7770492
          },
          "pointcloud_5.pcd": {
            "hash": "24b8355c63a7b80b178119e236c73e0e",
            "size": 9393148
          },
          "pointcloud_6.pcd": {
            "hash": "1495a9cef3fe14e3136ad6e3d9f526d7",
            "size": 9753212
          },
          "pointcloud_7.pcd": {
            "hash": "68a340e862482c60f19d3630768c4794",
            "size": 12083820
          },
          "pointcloud_8.pcd": {
            "hash": "d85c560f9c8d59227fee940b794ef4ab",
            "size": 12726636
          },
          "pointcloud_9.pcd": {
            "hash": "b2e77bd6cc0015dfda9e5e7b6418356f",
            "size": 14269596
          }
        },
        "position": {
          "position_0.json": {
            "hash": "e69477a7744bccdecb2b080c552f993b",
            "size": 255
          },
          "position_1.json": {
            "hash": "25df91a467e83eec4a210e1b3c4ebdcd",
            "size": 252
          },
          "position_10.json": {
            "hash": "caf428b5ecce6b29e85011e5cc2c6dea",
            "size": 252
          },
          "position_11.json": {
            "hash": "d413b45c59f10c454c1312af9627e1e2",
            "size": 247
          },
          "position_12.json": {
            "hash": "132ac3e0da6e2a1f85ba5a07cedf2306",
            "size": 248
          },
          "position_13.json": {
            "hash": "c2437b79ab4837fa41cfb9f179512da9",
            "size": 251
          },
          "position_14.json": {
            "hash": "0af257aec5d91a7728ebab01d1dc2d7f",
            "size": 250
          },
          "position_15.json": {
            "hash": "3f67a370856880ad984cba898b7a72d6",
            "size": 250
          },
          "position_16.json": {
            "hash": "b3c912660fb2c4c381d4d6df4eb4d1a2",
            "size": 248
          },
          "position_17.json": {
            "hash": "d3d2a0624cbb638b0634e224ae00174f",
            "size": 252
          },
          "position_18.json": {
            "hash": "3b781d4dd58455dee513797caa787873",
            "size": 252
          },
          "position_19.json": {
            "hash": "f0767e5fd24c024b41e6aba6db6e4e27",
            "size": 250
          },
          "position_2.json": {
            "hash": "59418a18523ce909a29f996e0c2564f3",
            "size": 248
          },
          "position_20.json": {
            "hash": "127a1684c3353509a7eb568475678dc2",
            "size": 251
          },
          "position_21.json": {
            "hash": "8b846c895034492570fedcc9760cf465",
            "size": 251
          },
          "position_22.json": {
            "hash": "79fa90b30b8047dd2ea7e31f88af4def",
            "size": 252
          },
          "position_23.json": {
            "hash": "5cbc8ea8fae8b9042b399619c30a27c1",
            "size": 248
          },
          "position_3.json": {
            "hash": "65d30762cd09c4c6e7b2861d6639e907",
            "size": 251
          },
          "position_4.json": {
            "hash": "68b80a90d5f64e98ba2b4435b6936fde",
            "size": 251
          },
          "position_5.json": {
            "hash": "e99420aca01ab98c885c6a63aba5cc54",
            "size": 250
          },
          "position_6.json": {
            "hash": "bb598418ee2f4e999cfed32a0de01bed",
            "size": 250
          },
          "position_7.json": {
            "hash": "f281c04276c7977247ea11162978df5d",
            "size": 250
          },
          "position_8.json": {
            "hash": "b6efc6160aa25c421a6c5fafc9b516ca",
            "size": 249
          },
          "position_9.json": {
            "hash": "ddea37ec6349b6a18d6cbb00b835323a",
            "size": 250
          }
        }
      }
    }
  }
}
